Practicas_GHDL/MyBooleanALU/MyBooleanALU.vhd
-- File:
-- Author:
-- Date:
-- Revision:
-- Description:

library ieee;
use ieee.std_logic_1164.all;
use ieee.numeric_std.all;
-- use ieee.numeric_bit.all;
-- use std.textio.all;
-- use ieee.std_logic_textio.all;


-- ENTITY DECLARATION ------------------------------------------------------------------------------
entity MyBooleanALU is

    port ( 
      piData1 : in STD_LOGIC_VECTOR (3 downto 0);
      piData2 : in STD_LOGIC_VECTOR (3 downto 0);
      piOpCode : in STD_LOGIC_VECTOR (2 downto 0);
      poResult : out STD_LOGIC_VECTOR (3 downto 0);
      poZeroFlag : out STD_LOGIC;
      poOneFlag : out STD_LOGIC
    );
end entity MyBooleanALU;


-- ARCHITECTURE DECLARATION ------------------------------------------------------------------------
architecture A_MyBooleanALU of MyBooleanALU is
signal result : STD_LOGIC_VECTOR (3 downto 0);
begin
    with piOpCode select
        result <=   piData1 and piData2  when "000",
                    piData1 nand piData2 when "001",
                    piData1 or piData2   when "010",
                    piData1 nor piData2  when "011",
                    piData1 xor piData2  when "100",
                    piData1 xnor piData2 when "101",
                    "1111"               when "110",
                    "0000" when others;
                    
    poZeroFlag <= '1' WHEN result = "0000" else '0';
    poOneFlag  <= '1' WHEN result = "1111" else '0';
    poResult <= result;
end architecture A_MyBooleanALU;

Practicas_GHDL/MyBooleanALU/MyBooleanALU_tb.vhd
-- File:
-- Author:
-- Date:
-- Revision:
-- Description:

library IEEE;
use IEEE.STD_LOGIC_1164.ALL;
use IEEE.NUMERIC_STD.ALL;
use IEEE.NUMERIC_BIT.ALL;


-- ENTITY DECLARATION ------------------------------------------------------------------------------
entity MyBooleanALU_TB is
      -- generic / port / local declatations
end entity MyBooleanALU_TB;


-- ARCHITECTURE DECLARATION ------------------------------------------------------------------------
architecture Behavioral of MyBooleanALU_TB is
     component MyBooleanALU is

              
    port ( 
      piData1 : in STD_LOGIC_VECTOR (3 downto 0);
      piData2 : in STD_LOGIC_VECTOR (3 downto 0);
      piOpCode : in STD_LOGIC_VECTOR (2 downto 0);
      poResult : out STD_LOGIC_VECTOR (3 downto 0);
      poZeroFlag : out STD_LOGIC;
      poOneFlag : out STD_LOGIC
    );
    end component MyBooleanALU;
     
    signal Data1 : STD_LOGIC_VECTOR (3 downto 0);
    signal Data2 : STD_LOGIC_VECTOR (3 downto 0);
    signal OpCode : STD_LOGIC_VECTOR (2 downto 0);
    signal Result : STD_LOGIC_VECTOR (3 downto 0);
    signal ZeroFlag : STD_LOGIC;
    signal OneFlag : STD_LOGIC;
       
begin
    instMyBooleanALU: MyBooleanALU
--         Generic map ( N => 2 )
        Port map ( piData1 => Data1,
                    piData2 => Data2,
                    piOpCode => OpCode,
                    poResult => Result,
                    poZeroFlag => ZeroFlag,
                    poOneFlag => OneFlag
                   );
                    

    process
    begin
    Data1 <= "0110";
    Data2 <= "1011";
    
    OpCode <= "000";
    wait for 10 ns;
    OpCode <= "001";
    wait for 10 ns;
    OpCode <= "010";
    wait for 10 ns;
    OpCode <= "011";
    wait for 10 ns;
    OpCode <= "100";
    wait for 10 ns;
    OpCode <= "101";
    wait for 10 ns;
    OpCode <= "110";
    wait for 10 ns;
    OpCode <= "111";
    wait for 10 ns;
    OpCode <= "000";
    wait;

    end process;                   
     
end architecture Behavioral;

Practicas_GHDL/MyBooleanALU/MyBooleanALU_tb.vcd
$date
  Sat Sep 14 23:15:40 2024
$end
$version
  GHDL v0
$end
$timescale
  1 fs
$end
$scope module standard $end
$upscope $end
$scope module std_logic_1164 $end
$upscope $end
$scope module numeric_std $end
$upscope $end
$scope module numeric_bit $end
$upscope $end
$scope module mybooleanalu_tb $end
$var reg 4 ! data1[3:0] $end
$var reg 4 " data2[3:0] $end
$var reg 3 # opcode[2:0] $end
$var reg 4 $ result[3:0] $end
$var reg 1 % zeroflag $end
$var reg 1 & oneflag $end
$scope module instmybooleanalu $end
$var reg 4 ' pidata1[3:0] $end
$var reg 4 ( pidata2[3:0] $end
$var reg 3 ) piopcode[2:0] $end
$var reg 4 * poresult[3:0] $end
$var reg 1 + pozeroflag $end
$var reg 1 , pooneflag $end
$var reg 4 - result[3:0] $end
$upscope $end
$upscope $end
$enddefinitions $end
#0
b0110 !
b1011 "
b000 #
b0010 $
0%
0&
b0110 '
b1011 (
b000 )
b0010 *
0+
0,
b0010 -
#10000000
b001 #
b1101 $
b001 )
b1101 *
b1101 -
#20000000
b010 #
b1111 $
1&
b010 )
b1111 *
1,
b1111 -
#30000000
b011 #
b0000 $
1%
0&
b011 )
b0000 *
1+
0,
b0000 -
#40000000
b100 #
b1101 $
0%
b100 )
b1101 *
0+
b1101 -
#50000000
b101 #
b0010 $
b101 )
b0010 *
b0010 -
#60000000
b110 #
b1111 $
1&
b110 )
b1111 *
1,
b1111 -
#70000000
b111 #
b0000 $
1%
0&
b111 )
b0000 *
1+
0,
b0000 -
#80000000
b000 #
b0010 $
0%
b000 )
b0010 *
0+
b0010 -
