Practicas_GHDL/ModuleCounter/ModuleCounter.vhd
----------------------------------------------------------------------------------
-- Company: 
-- Engineer: 
-- 
-- Create Date: 10/17/2024 05:32:34 PM
-- Design Name: 
-- Module Name: ModuleCounter - Behavioral
-- Project Name: 
-- Target Devices: 
-- Tool Versions: 
-- Description: 
-- 
-- Dependencies: 
-- 
-- Revision:
-- Revision 0.01 - File Created
-- Additional Comments:
-- 
----------------------------------------------------------------------------------


library IEEE;
use IEEE.STD_LOGIC_1164.ALL;

use ieee.numeric_std.all;

entity ModuleCounter is
    Generic (NBits: natural := 25;
	         Max: natural := 25000000);
    Port (  piMCClk : in STD_LOGIC;
            piMCEna : in STD_LOGIC;
            piMCRst : in STD_LOGIC;
            poMCO : out std_logic;
            poMCH : out std_logic
		 );	
end ModuleCounter;

architecture A_ModuleCounter of ModuleCounter is

signal auxCount: unsigned(NBits-1 downto 0);
constant half: NATURAL := Max/2;

begin

    process(piMCClk, piMCEna, piMCRst)
    begin
        if piMCRst = '1' then
            auxCount <= to_unsigned(0, NBits);
        elsif rising_edge(piMCClk) then
			if piMCEna = '1' then
				auxCount <= auxCount + to_unsigned(1, NBits);
				if auxCount = to_unsigned(Max-1, NBits) then
					auxCount <= to_unsigned(0, NBits);
				end if;
			end if;	
        end if;        
	end process;
	
	poMCO <= '1' when auxCount = to_unsigned(0, NBits) else '0';
    poMCH <= '1' when auxCount = to_unsigned(half, NBits) else '0';
	
    
end A_ModuleCounter;

Practicas_GHDL/ModuleCounter/ModuleCounter_TB.vhd
----------------------------------------------------------------------------------
-- Company: 
-- Engineer: 
-- 
-- Create Date: 10/17/2024 05:36:16 PM
-- Design Name: 
-- Module Name: ModuleCounter_tb - Behavioral
-- Project Name: 
-- Target Devices: 
-- Tool Versions: 
-- Description: 
-- 
-- Dependencies: 
-- 
-- Revision:
-- Revision 0.01 - File Created
-- Additional Comments:
-- 
----------------------------------------------------------------------------------
library IEEE;

use ieee.std_logic_1164.all;
use ieee.numeric_std.all;

entity ModuleCounter_TB is
end ModuleCounter_TB;


architecture A_ModuleCounter_TB of ModuleCounter_TB is

component ModuleCounter is
    Generic (NBits: natural;
	         Max: natural);
    Port (  piMCClk : in STD_LOGIC;
            piMCEna : in STD_LOGIC;
            piMCRst : in STD_LOGIC;
            poMCO : out std_logic;
            poMCH : out std_logic
		 );	
end component ModuleCounter;

signal clk, ena, rst, x1, x2, x3, x4, xH1, xH2, xH3, xH4: std_logic;

begin
	
	instBb1: ModuleCounter
		generic map( NBits => 3, Max => 1)
		port map(piMCClk => clk, piMCEna => ena, piMCRst => rst, poMCO => x1, poMCH => xH1);

	instBb2: ModuleCounter
		generic map( NBits => 3, Max => 2)
		port map(piMCClk => clk, piMCEna => ena, piMCRst => rst, poMCO => x2, poMCH => xH2);
	
	instBb3: ModuleCounter
		generic map( NBits => 3, Max => 3)
		port map(piMCClk => clk, piMCEna => ena, piMCRst => rst, poMCO => x3, poMCH => xH3);

	instBb4: ModuleCounter
		generic map( NBits => 3, Max => 4)
		port map(piMCClk => clk, piMCEna => ena, piMCRst => rst, poMCO => x4, poMCH => xH4);
		
	pClk: process
	begin
		clk <= '1';
		wait for 10 ns;
		clk <= '0';
		wait for 10 ns;
	end process;	
	
	
	process
	begin
		rst <= '1';
		ena <= '0';
		wait for 40 ns;
		rst <= '0';
		wait until falling_edge(clk);
		ena <= '1';
		wait for 1000 ns;
		wait until falling_edge(clk);
		ena <= '0';
		wait;
	end process;
    
    
end A_ModuleCounter_TB;

Practicas_GHDL/ModuleCounter/ModuleCounter_TB.vcd
$date
  Sun Nov 10 10:34:09 2024
$end
$version
  GHDL v0
$end
$timescale
  1 fs
$end
$scope module standard $end
$upscope $end
$scope module std_logic_1164 $end
$upscope $end
$scope module numeric_std $end
$upscope $end
$scope module modulecounter_tb $end
$var reg 1 ! clk $end
$var reg 1 " ena $end
$var reg 1 # rst $end
$var reg 1 $ x1 $end
$var reg 1 % x2 $end
$var reg 1 & x3 $end
$var reg 1 ' x4 $end
$var reg 1 ( xh1 $end
$var reg 1 ) xh2 $end
$var reg 1 * xh3 $end
$var reg 1 + xh4 $end
$scope module instbb1 $end
$var reg 1 , pimcclk $end
$var reg 1 - pimcena $end
$var reg 1 . pimcrst $end
$var reg 1 / pomco $end
$var reg 1 0 pomch $end
$var reg 3 1 auxcount[2:0] $end
$upscope $end
$scope module instbb2 $end
$var reg 1 2 pimcclk $end
$var reg 1 3 pimcena $end
$var reg 1 4 pimcrst $end
$var reg 1 5 pomco $end
$var reg 1 6 pomch $end
$var reg 3 7 auxcount[2:0] $end
$upscope $end
$scope module instbb3 $end
$var reg 1 8 pimcclk $end
$var reg 1 9 pimcena $end
$var reg 1 : pimcrst $end
$var reg 1 ; pomco $end
$var reg 1 < pomch $end
$var reg 3 = auxcount[2:0] $end
$upscope $end
$scope module instbb4 $end
$var reg 1 > pimcclk $end
$var reg 1 ? pimcena $end
$var reg 1 @ pimcrst $end
$var reg 1 A pomco $end
$var reg 1 B pomch $end
$var reg 3 C auxcount[2:0] $end
$upscope $end
$upscope $end
$enddefinitions $end
#0
1!
0"
1#
1$
1%
1&
1'
1(
0)
0*
0+
1,
0-
1.
1/
10
b000 1
12
03
14
15
06
b000 7
18
09
1:
1;
0<
b000 =
1>
0?
1@
1A
0B
b000 C
#10000000
0!
0,
02
08
0>
#20000000
1!
1,
12
18
1>
#30000000
0!
0,
02
08
0>
#40000000
1!
0#
1,
0.
12
04
18
0:
1>
0@
#50000000
0!
1"
0,
1-
02
13
08
19
0>
1?
#60000000
1!
0%
0&
0'
1)
1*
1,
12
05
16
b001 7
18
0;
1<
b001 =
1>
0A
b001 C
#70000000
0!
0,
02
08
0>
#80000000
1!
1%
0)
0*
1+
1,
12
15
06
b000 7
18
0<
b010 =
1>
1B
b010 C
#90000000
0!
0,
02
08
0>
#100000000
1!
0%
1&
1)
0+
1,
12
05
16
b001 7
18
1;
b000 =
1>
0B
b011 C
#110000000
0!
0,
02
08
0>
#120000000
1!
1%
0&
1'
0)
1*
1,
12
15
06
b000 7
18
0;
1<
b001 =
1>
1A
b000 C
#130000000
0!
0,
02
08
0>
#140000000
1!
0%
0'
1)
0*
1,
12
05
16
b001 7
18
0<
b010 =
1>
0A
b001 C
#150000000
0!
0,
02
08
0>
#160000000
1!
1%
1&
0)
1+
1,
12
15
06
b000 7
18
1;
b000 =
1>
1B
b010 C
#170000000
0!
0,
02
08
0>
#180000000
1!
0%
0&
1)
1*
0+
1,
12
05
16
b001 7
18
0;
1<
b001 =
1>
0B
b011 C
#190000000
0!
0,
02
08
0>
#200000000
1!
1%
1'
0)
0*
1,
12
15
06
b000 7
18
0<
b010 =
1>
1A
b000 C
#210000000
0!
0,
02
08
0>
#220000000
1!
0%
1&
0'
1)
1,
12
05
16
b001 7
18
1;
b000 =
1>
0A
b001 C
#230000000
0!
0,
02
08
0>
#240000000
1!
1%
0&
0)
1*
1+
1,
12
15
06
b000 7
18
0;
1<
b001 =
1>
1B
b010 C
#250000000
0!
0,
02
08
0>
#260000000
1!
0%
1)
0*
0+
1,
12
05
16
b001 7
18
0<
b010 =
1>
0B
b011 C
#270000000
0!
0,
02
08
0>
#280000000
1!
1%
1&
1'
0)
1,
12
15
06
b000 7
18
1;
b000 =
1>
1A
b000 C
#290000000
0!
0,
02
08
0>
#300000000
1!
0%
0&
0'
1)
1*
1,
12
05
16
b001 7
18
0;
1<
b001 =
1>
0A
b001 C
#310000000
0!
0,
02
08
0>
#320000000
1!
1%
0)
0*
1+
1,
12
15
06
b000 7
18
0<
b010 =
1>
1B
b010 C
#330000000
0!
0,
02
08
0>
#340000000
1!
0%
1&
1)
0+
1,
12
05
16
b001 7
18
1;
b000 =
1>
0B
b011 C
#350000000
0!
0,
02
08
0>
#360000000
1!
1%
0&
1'
0)
1*
1,
12
15
06
b000 7
18
0;
1<
b001 =
1>
1A
b000 C
#370000000
0!
0,
02
08
0>
#380000000
1!
0%
0'
1)
0*
1,
12
05
16
b001 7
18
0<
b010 =
1>
0A
b001 C
#390000000
0!
0,
02
08
0>
#400000000
1!
1%
1&
0)
1+
1,
12
15
06
b000 7
18
1;
b000 =
1>
1B
b010 C
#410000000
0!
0,
02
08
0>
#420000000
1!
0%
0&
1)
1*
0+
1,
12
05
16
b001 7
18
0;
1<
b001 =
1>
0B
b011 C
#430000000
0!
0,
02
08
0>
#440000000
1!
1%
1'
0)
0*
1,
12
15
06
b000 7
18
0<
b010 =
1>
1A
b000 C
#450000000
0!
0,
02
08
0>
#460000000
1!
0%
1&
0'
1)
1,
12
05
16
b001 7
18
1;
b000 =
1>
0A
b001 C
#470000000
0!
0,
02
08
0>
#480000000
1!
1%
0&
0)
1*
1+
1,
12
15
06
b000 7
18
0;
1<
b001 =
1>
1B
b010 C
#490000000
0!
0,
02
08
0>
#500000000
1!
0%
1)
0*
0+
1,
12
05
16
b001 7
18
0<
b010 =
1>
0B
b011 C
#510000000
0!
0,
02
08
0>
#520000000
1!
1%
1&
1'
0)
1,
12
15
06
b000 7
18
1;
b000 =
1>
1A
b000 C
#530000000
0!
0,
02
08
0>
#540000000
1!
0%
0&
0'
1)
1*
1,
12
05
16
b001 7
18
0;
1<
b001 =
1>
0A
b001 C
#550000000
0!
0,
02
08
0>
#560000000
1!
1%
0)
0*
1+
1,
12
15
06
b000 7
18
0<
b010 =
1>
1B
b010 C
#570000000
0!
0,
02
08
0>
#580000000
1!
0%
1&
1)
0+
1,
12
05
16
b001 7
18
1;
b000 =
1>
0B
b011 C
#590000000
0!
0,
02
08
0>
#600000000
1!
1%
0&
1'
0)
1*
1,
12
15
06
b000 7
18
0;
1<
b001 =
1>
1A
b000 C
#610000000
0!
0,
02
08
0>
#620000000
1!
0%
0'
1)
0*
1,
12
05
16
b001 7
18
0<
b010 =
1>
0A
b001 C
#630000000
0!
0,
02
08
0>
#640000000
1!
1%
1&
0)
1+
1,
12
15
06
b000 7
18
1;
b000 =
1>
1B
b010 C
#650000000
0!
0,
02
08
0>
#660000000
1!
0%
0&
1)
1*
0+
1,
12
05
16
b001 7
18
0;
1<
b001 =
1>
0B
b011 C
#670000000
0!
0,
02
08
0>
#680000000
1!
1%
1'
0)
0*
1,
12
15
06
b000 7
18
0<
b010 =
1>
1A
b000 C
#690000000
0!
0,
02
08
0>
#700000000
1!
0%
1&
0'
1)
1,
12
05
16
b001 7
18
1;
b000 =
1>
0A
b001 C
#710000000
0!
0,
02
08
0>
#720000000
1!
1%
0&
0)
1*
1+
1,
12
15
06
b000 7
18
0;
1<
b001 =
1>
1B
b010 C
#730000000
0!
0,
02
08
0>
#740000000
1!
0%
1)
0*
0+
1,
12
05
16
b001 7
18
0<
b010 =
1>
0B
b011 C
#750000000
0!
0,
02
08
0>
#760000000
1!
1%
1&
1'
0)
1,
12
15
06
b000 7
18
1;
b000 =
1>
1A
b000 C
#770000000
0!
0,
02
08
0>
#780000000
1!
0%
0&
0'
1)
1*
1,
12
05
16
b001 7
18
0;
1<
b001 =
1>
0A
b001 C
#790000000
0!
0,
02
08
0>
#800000000
1!
1%
0)
0*
1+
1,
12
15
06
b000 7
18
0<
b010 =
1>
1B
b010 C
#810000000
0!
0,
02
08
0>
#820000000
1!
0%
1&
1)
0+
1,
12
05
16
b001 7
18
1;
b000 =
1>
0B
b011 C
#830000000
0!
0,
02
08
0>
#840000000
1!
1%
0&
1'
0)
1*
1,
12
15
06
b000 7
18
0;
1<
b001 =
1>
1A
b000 C
#850000000
0!
0,
02
08
0>
#860000000
1!
0%
0'
1)
0*
1,
12
05
16
b001 7
18
0<
b010 =
1>
0A
b001 C
#870000000
0!
0,
02
08
0>
#880000000
1!
1%
1&
0)
1+
1,
12
15
06
b000 7
18
1;
b000 =
1>
1B
b010 C
#890000000
0!
0,
02
08
0>
#900000000
1!
0%
0&
1)
1*
0+
1,
12
05
16
b001 7
18
0;
1<
b001 =
1>
0B
b011 C
#910000000
0!
0,
02
08
0>
#920000000
1!
1%
1'
0)
0*
1,
12
15
06
b000 7
18
0<
b010 =
1>
1A
b000 C
#930000000
0!
0,
02
08
0>
#940000000
1!
0%
1&
0'
1)
1,
12
05
16
b001 7
18
1;
b000 =
1>
0A
b001 C
#950000000
0!
0,
02
08
0>
#960000000
1!
1%
0&
0)
1*
1+
1,
12
15
06
b000 7
18
0;
1<
b001 =
1>
1B
b010 C
#970000000
0!
0,
02
08
0>
#980000000
1!
0%
1)
0*
0+
1,
12
05
16
b001 7
18
0<
b010 =
1>
0B
b011 C
#990000000
0!
0,
02
08
0>
#1000000000
1!
1%
1&
1'
0)
1,
12
15
06
b000 7
18
1;
b000 =
1>
1A
b000 C
