Practicas_GHDL/MyVoter/MyVoter.vhd
-- File:
-- Author:
-- Date:
-- Revision:
-- Description:

library ieee;
use ieee.std_logic_1164.all;
use ieee.numeric_std.all;
-- use ieee.numeric_bit.all;
-- use std.textio.all;
-- use ieee.std_logic_textio.all;


-- ENTITY DECLARATION ------------------------------------------------------------------------------
entity MyVoter is
    -- generic / port / local declatations
--     generic (N: Natural := 4);
    
    port ( 
        piX: in std_logic;
        piY: in std_logic;
        piZ: in std_logic;
        poOUT: out std_logic
--         poOUT: out std_logic_vector(N-1 downto 0)  
    );
end entity MyVoter;


-- ARCHITECTURE DECLARATION ------------------------------------------------------------------------
architecture A_MyVoter of MyVoter is
    -- local declarations (use function type file component constant signal procedure subtype alias)
--     signal aux : std_logic;
    signal aux : std_logic_vector(2 downto 0);
begin
    aux <= piX & piY & piZ;
    with aux select
    poOUT <=  '0' when "000",
              '0' when "001",
              '0' when "010",
              '1' when "011",
              '0' when "100",
              '1' when "101",
              '1' when "110",
              '1' when "111",
              '0' when others;
end architecture A_MyVoter;

Practicas_GHDL/MyVoter/MyVoter_tb.vhd
-- File:
-- Author:
-- Date:
-- Revision:
-- Description:

library IEEE;
use IEEE.STD_LOGIC_1164.ALL;
use IEEE.NUMERIC_STD.ALL;
use IEEE.NUMERIC_BIT.ALL;


-- ENTITY DECLARATION ------------------------------------------------------------------------------
entity MyVoter_TB is
      -- generic / port / local declatations
end entity MyVoter_TB;


-- ARCHITECTURE DECLARATION ------------------------------------------------------------------------
architecture Behavioral of MyVoter_TB is
     component MyVoter is
--         Generic ( N: natural
--                 );
              
    port ( 
        piX: in std_logic;
        piY: in std_logic;
        piZ: in std_logic;
        poOUT: out std_logic
    );
     end component MyVoter;
     
     signal X : std_logic;
     signal Y : std_logic;
     signal Z : std_logic;
     signal O : std_logic;
           
begin
    instMyVoter: MyVoter
--         Generic map ( N => 2 )
        Port map ( piX => X,
                   piY => Y,
                   piZ => Z,
                   poOUT => O
                   );
                    
--     pCLK: process 
--     begin
--         CLK <= '1';
--         wait for 10 ns;
--         CLK <= '0';
--         wait for 10 ns;
--     end process pCLK; 
    
    process
    begin
--         ENA <= '0';
--         wait until falling_edge(CLK);
--         RST <= '1';
--         wait until falling_edge(CLK);
--         RST <= '0';
--         ENA <= '1';
--         wait for 85 ns;
--         ENA <= '0';
--         wait until falling_edge(CLK);
--         RST <= '1';
--         wait until falling_edge(CLK);
--         wait;
    X <='0';
    Y <='0';
    Z <='0';
    wait for 10 ns;
    X <='0';
    Y <='0';
    Z <='1';
    wait for 10 ns;
    X <='0';
    Y <='1';
    Z <='0';
    wait for 10 ns;
    X <='0';
    Y <='1';
    Z <='1';
    wait for 10 ns;
    X <='1';
    Y <='0';
    Z <='0';
    wait for 10 ns;
    X <='1';
    Y <='0';
    Z <='1';
    wait for 10 ns;
    X <='1';
    Y <='1';
    Z <='0';
    wait for 10 ns;
    X <='1';
    Y <='1';
    Z <='1';
    wait for 10 ns;
    X <='0';
    Y <='0';
    Z <='0';
    wait;
    end process;                   
     
end architecture Behavioral;

Practicas_GHDL/MyVoter/MyVoter_tb.vcd
$date
  Fri Sep 13 16:58:03 2024
$end
$version
  GHDL v0
$end
$timescale
  1 fs
$end
$scope module standard $end
$upscope $end
$scope module std_logic_1164 $end
$upscope $end
$scope module numeric_std $end
$upscope $end
$scope module numeric_bit $end
$upscope $end
$scope module myvoter_tb $end
$var reg 1 ! x $end
$var reg 1 " y $end
$var reg 1 # z $end
$var reg 1 $ o $end
$scope module instmyvoter $end
$var reg 1 % pix $end
$var reg 1 & piy $end
$var reg 1 ' piz $end
$var reg 1 ( poout $end
$var reg 3 ) aux[2:0] $end
$upscope $end
$upscope $end
$enddefinitions $end
#0
0!
0"
0#
0$
0%
0&
0'
0(
b000 )
#10000000
1#
1'
b001 )
#20000000
1"
0#
1&
0'
b010 )
#30000000
1#
1$
1'
1(
b011 )
#40000000
1!
0"
0#
0$
1%
0&
0'
0(
b100 )
#50000000
1#
1$
1'
1(
b101 )
#60000000
1"
0#
1&
0'
b110 )
#70000000
1#
1'
b111 )
#80000000
0!
0"
0#
0$
0%
0&
0'
0(
b000 )
