Practicas_GHDL/MyFullADD/MyFullADD.vhd
-- File:
-- Author:
-- Date:
-- Revision:
-- Description:

library ieee;
use ieee.std_logic_1164.all;
use ieee.numeric_std.all;
-- use ieee.numeric_bit.all;
-- use std.textio.all;
-- use ieee.std_logic_textio.all;


-- ENTITY DECLARATION ------------------------------------------------------------------------------
entity MyFullADD is
    -- generic / port / local declatations
--     generic (N: Natural := 4);
    
    port ( 
        piA: in std_logic;
        piB: in std_logic;
        piCi: in std_logic;
        poS: out std_logic;
        poCo: out std_logic
--         poOUT: out std_logic_vector(N-1 downto 0)  
    );
end entity MyFullADD;


-- ARCHITECTURE DECLARATION ------------------------------------------------------------------------
architecture A_MyFullADD of MyFullADD is
    -- local declarations (use function type file component constant signal procedure subtype alias)
--     signal aux : std_logic;

begin
    poS <= piA xor piB xor piCi;
    poCo <= (piA and piB) or (piCi and (piA xor piB));
end architecture A_MyFullADD;

Practicas_GHDL/MyFullADD/MyFullADD_tb.vhd
-- File:
-- Author:
-- Date:
-- Revision:
-- Description:

library IEEE;
use IEEE.STD_LOGIC_1164.ALL;
use IEEE.NUMERIC_STD.ALL;
use IEEE.NUMERIC_BIT.ALL;


-- ENTITY DECLARATION ------------------------------------------------------------------------------
entity MyFullADD_TB is
      -- generic / port / local declatations
end entity MyFullADD_TB;


-- ARCHITECTURE DECLARATION ------------------------------------------------------------------------
architecture Behavioral of MyFullADD_TB is
     component MyFullADD is
--         Generic ( N: natural
--                 );
              
    port ( 
        piA: in std_logic;
        piB: in std_logic;
        piCi: in std_logic;
        poS: out std_logic;
        poCo: out std_logic
    );
     end component MyFullADD;
     
     signal A : std_logic;
     signal B : std_logic;
     signal Ci : std_logic;
     signal S : std_logic;
     signal Co : std_logic;
           
begin
    instMyFullADD: MyFullADD
--         Generic map ( N => 2 )
        Port map ( piA => A,
                   piB => B,
                   piCi => Ci,
                   poS => S,
                   poCo => Co
                   );
                    
--     pCLK: process 
--     begin
--         CLK <= '1';
--         wait for 10 ns;
--         CLK <= '0';
--         wait for 10 ns;
--     end process pCLK; 
    
    process
    begin
--         ENA <= '0';
--         wait until falling_edge(CLK);
--         RST <= '1';
--         wait until falling_edge(CLK);
--         RST <= '0';
--         ENA <= '1';
--         wait for 85 ns;
--         ENA <= '0';
--         wait until falling_edge(CLK);
--         RST <= '1';
--         wait until falling_edge(CLK);
--         wait;
    A <='0';
    B <='0';
    Ci <='0';
    wait for 10 ns;
    A <='0';
    B <='0';
    Ci <='1';
    wait for 10 ns;
    A <='0';
    B <='1';
    Ci <='0';
    wait for 10 ns;
    A <='0';
    B <='1';
    Ci <='1';
    wait for 10 ns;
    A <='1';
    B <='0';
    Ci <='0';
    wait for 10 ns;
    A <='1';
    B <='0';
    Ci <='1';
    wait for 10 ns;
    A <='1';
    B <='1';
    Ci <='0';
    wait for 10 ns;
    A <='1';
    B <='1';
    Ci <='1';
    wait for 10 ns;
    A <='0';
    B <='0';
    Ci <='0';
    wait;
    end process;                   
     
end architecture Behavioral;

Practicas_GHDL/MyFullADD/MyFullADD_tb.vcd
$date
  Sat Sep 21 15:06:28 2024
$end
$version
  GHDL v0
$end
$timescale
  1 fs
$end
$scope module standard $end
$upscope $end
$scope module std_logic_1164 $end
$upscope $end
$scope module numeric_std $end
$upscope $end
$scope module numeric_bit $end
$upscope $end
$scope module myfulladd_tb $end
$var reg 1 ! a $end
$var reg 1 " b $end
$var reg 1 # ci $end
$var reg 1 $ s $end
$var reg 1 % co $end
$scope module instmyfulladd $end
$var reg 1 & pia $end
$var reg 1 ' pib $end
$var reg 1 ( pici $end
$var reg 1 ) pos $end
$var reg 1 * poco $end
$upscope $end
$upscope $end
$enddefinitions $end
#0
0!
0"
0#
0$
0%
0&
0'
0(
0)
0*
#10000000
1#
1$
1(
1)
#20000000
1"
0#
1'
0(
#30000000
1#
0$
1%
1(
0)
1*
#40000000
1!
0"
0#
1$
0%
1&
0'
0(
1)
0*
#50000000
1#
0$
1%
1(
0)
1*
#60000000
1"
0#
1'
0(
#70000000
1#
1$
1(
1)
#80000000
0!
0"
0#
0$
0%
0&
0'
0(
0)
0*
