Practicas_GHDL/MyDiv3/MyDiv3.vhd
-- File:
-- Author:
-- Date:
-- Revision:
-- Description:

library ieee;
use ieee.std_logic_1164.all;
use ieee.numeric_std.all;
-- use ieee.numeric_bit.all;
-- use std.textio.all;
-- use ieee.std_logic_textio.all;


-- ENTITY DECLARATION ------------------------------------------------------------------------------
entity MyDiv3 is
    -- generic / port / local declatations
--     generic (N: Natural := 4);
    
    port ( 
        piBCD: in std_logic_vector(3 downto 0);
        poOUT: out std_logic_vector(2 downto 0)  
    );
end entity MyDiv3;


-- ARCHITECTURE DECLARATION ------------------------------------------------------------------------
architecture A_MyDiv3 of MyDiv3 is
    -- local declarations (use function type file component constant signal procedure subtype alias)
--     signal aux : std_logic;
    
begin
    with piBCD select
    poOUT <=  "001" when "0011",
              "001" when "0100",
              "001" when "0101",
              "010" when "0110",
              "010" when "0111",
              "010" when "1000",
              "011" when "1001",
              "011" when "1010",
              "011" when "1011",
              "000" when others;
end architecture A_MyDiv3;

Practicas_GHDL/MyDiv3/MyDiv3_tb.vhd
-- File:
-- Author:
-- Date:
-- Revision:
-- Description:

library IEEE;
use IEEE.STD_LOGIC_1164.ALL;
use IEEE.NUMERIC_STD.ALL;
use IEEE.NUMERIC_BIT.ALL;


-- ENTITY DECLARATION ------------------------------------------------------------------------------
entity MyDiv3_TB is
      -- generic / port / local declatations
end entity MyDiv3_TB;


-- ARCHITECTURE DECLARATION ------------------------------------------------------------------------
architecture Behavioral of MyDiv3_TB is
     component MyDiv3 is
--         Generic ( N: natural
--                 );
              
    port ( 
        piBCD: in std_logic_vector(3 downto 0);
        poOUT: out std_logic_vector(2 downto 0)  
    );
     end component MyDiv3;
     
     signal A : std_logic_vector(3 downto 0);
     signal B : std_logic_vector(2 downto 0);
           
begin
    insMyDiv3: MyDiv3
--         Generic map ( N => 2 )
        Port map ( piBCD => A,
                   poOUT => B
                   );
    
    process
    begin

    A <= "0000";
    wait for 10 ns;
    A <= "0001";
    wait for 10 ns;
    A <= "0010";
    wait for 10 ns;
    A <= "0011";
    wait for 10 ns;
    A <= "0100";
    wait for 10 ns;
    A <= "0101";
    wait for 10 ns;
    A <= "0110";
    wait for 10 ns;
    A <= "0111";
    wait for 10 ns;
    A <= "1000";
    wait for 10 ns;
    A <= "1001";
    wait for 10 ns;
    A <= "1010";
    wait for 10 ns;
    A <= "1011";
    wait for 10 ns;
    A <= "1100";
    wait for 10 ns;
    A <= "1101";
    wait for 10 ns;
    A <= "1110";
    wait for 10 ns;
    A <= "1111";
    wait for 10 ns;
    A <= "0000";
    wait;
    end process;                   
     
end architecture Behavioral;

Practicas_GHDL/MyDiv3/MyDiv3_tb.vcd
$date
  Fri Sep 13 17:32:34 2024
$end
$version
  GHDL v0
$end
$timescale
  1 fs
$end
$scope module standard $end
$upscope $end
$scope module std_logic_1164 $end
$upscope $end
$scope module numeric_std $end
$upscope $end
$scope module numeric_bit $end
$upscope $end
$scope module mydiv3_tb $end
$var reg 4 ! a[3:0] $end
$var reg 3 " b[2:0] $end
$scope module insmydiv3 $end
$var reg 4 # pibcd[3:0] $end
$var reg 3 $ poout[2:0] $end
$upscope $end
$upscope $end
$enddefinitions $end
#0
b0000 !
b000 "
b0000 #
b000 $
#10000000
b0001 !
b0001 #
#20000000
b0010 !
b0010 #
#30000000
b0011 !
b001 "
b0011 #
b001 $
#40000000
b0100 !
b0100 #
#50000000
b0101 !
b0101 #
#60000000
b0110 !
b010 "
b0110 #
b010 $
#70000000
b0111 !
b0111 #
#80000000
b1000 !
b1000 #
#90000000
b1001 !
b011 "
b1001 #
b011 $
#100000000
b1010 !
b1010 #
#110000000
b1011 !
b1011 #
#120000000
b1100 !
b000 "
b1100 #
b000 $
#130000000
b1101 !
b1101 #
#140000000
b1110 !
b1110 #
#150000000
b1111 !
b1111 #
#160000000
b0000 !
b0000 #
