Practicas_GHDL/MySquare3/MySquare3.vhd
-- File:
-- Author:
-- Date:
-- Revision:
-- Description:

library ieee;
use ieee.std_logic_1164.all;
use ieee.numeric_std.all;
-- use ieee.numeric_bit.all;
-- use std.textio.all;
-- use ieee.std_logic_textio.all;


-- ENTITY DECLARATION ------------------------------------------------------------------------------
entity MySquare3 is

    port ( 
        piBits: in std_logic_vector(2 downto 0);
        poResult: out std_logic_vector(5 downto 0)
    );
end entity MySquare3;


-- ARCHITECTURE DECLARATION ------------------------------------------------------------------------
architecture A_MySquare3 of MySquare3 is

begin
    with piBits select
    poResult <= "000001" when "001",
                "000100" when "010",
                "001001" when "011",
                "010000" when "100",
                "011001" when "101",
                "100100" when "110",
                "110001" when "111",
                "000000" when others;
end architecture A_MySquare3;

Practicas_GHDL/MySquare3/MySquare3_tb.vhd
-- File:
-- Author:
-- Date:
-- Revision:
-- Description:

library IEEE;
use IEEE.STD_LOGIC_1164.ALL;
use IEEE.NUMERIC_STD.ALL;
use IEEE.NUMERIC_BIT.ALL;


-- ENTITY DECLARATION ------------------------------------------------------------------------------
entity MySquare3_TB is
      -- generic / port / local declatations
end entity MySquare3_TB;


-- ARCHITECTURE DECLARATION ------------------------------------------------------------------------
architecture Behavioral of MySquare3_TB is
     component MySquare3 is

              
    port ( 
        piBits: in std_logic_vector(2 downto 0);
        poResult: out std_logic_vector(5 downto 0)
    );
     end component MySquare3;
     
     signal B : std_logic_vector(2 downto 0);
     signal R : std_logic_vector(5 downto 0);
           
begin
    instMySquare3: MySquare3
--         Generic map ( N => 2 )
        Port map ( piBits => B,
                   poResult => R
                   );
                    
    
    process
    begin

    B <= "000";
    wait for 10 ns;
    B <= "001";
    wait for 10 ns;
    B <= "010";
    wait for 10 ns;
    B <= "011";
    wait for 10 ns;
    B <= "100";
    wait for 10 ns;
    B <= "101";
    wait for 10 ns;
    B <= "110";
    wait for 10 ns;
    B <= "111";
    wait for 10 ns;
    B <= "000";
    wait;

    end process;                   
     
end architecture Behavioral;

Practicas_GHDL/MySquare3/MySquare3_tb.vcd
$date
  Sat Sep 14 22:34:47 2024
$end
$version
  GHDL v0
$end
$timescale
  1 fs
$end
$scope module standard $end
$upscope $end
$scope module std_logic_1164 $end
$upscope $end
$scope module numeric_std $end
$upscope $end
$scope module numeric_bit $end
$upscope $end
$scope module mysquare3_tb $end
$var reg 3 ! b[2:0] $end
$var reg 6 " r[5:0] $end
$scope module instmysquare3 $end
$var reg 3 # pibits[2:0] $end
$var reg 6 $ poresult[5:0] $end
$upscope $end
$upscope $end
$enddefinitions $end
#0
b000 !
b000000 "
b000 #
b000000 $
#10000000
b001 !
b000001 "
b001 #
b000001 $
#20000000
b010 !
b000100 "
b010 #
b000100 $
#30000000
b011 !
b001001 "
b011 #
b001001 $
#40000000
b100 !
b010000 "
b100 #
b010000 $
#50000000
b101 !
b011001 "
b101 #
b011001 $
#60000000
b110 !
b100100 "
b110 #
b100100 $
#70000000
b111 !
b110001 "
b111 #
b110001 $
#80000000
b000 !
b000000 "
b000 #
b000000 $
