Practicas_GHDL/MyHexDecoder/MyHexDecoder.vhd
library ieee;
use ieee.std_logic_1164.all;
use ieee.numeric_std.all;

entity MyHexDecoder is
    port ( 
        piData: in std_logic_vector(3 downto 0);
        poHexValue: out std_logic_vector(6 downto 0)
    );
end entity MyHexDecoder;
--           A B C D E F G
-- 0: 0000 : 1 1 1 1 1 1 0
-- 1: 0001 : 0 1 1 0 0 0 0
-- 2: 0010 : 1 1 0 1 1 0 1
-- 3: 0011 : 1 1 1 1 0 0 1
-- 4: 0100 : 0 1 1 0 0 1 1
-- 5: 0101 : 1 0 1 1 0 1 1
-- 6: 0110 : 1 0 1 1 1 1 1
-- 7: 0111 : 1 1 1 0 0 0 0
-- 8: 1000 : 1 1 1 1 1 1 1
-- 9: 1001 : 1 1 1 1 0 1 1
-- A: 1010 : 1 1 1 0 1 1 1
-- B: 1011 : 0 0 1 1 1 1 1
-- C: 1100 : 1 0 0 1 1 1 0
-- D: 1101 : 0 1 1 1 1 0 1
-- E: 1110 : 1 0 0 1 1 1 1
-- F: 1111 : 1 0 0 0 1 1 1

architecture A_MyHexDecoder of MyHexDecoder is

begin
    with piData select
        poHexValue <= "1111110" when "0000",
                      "0110000" when "0001",
                      "1101101" when "0010",
                      "1111001" when "0011",
                      "0110011" when "0100",
                      "1011011" when "0101",
                      "1011111" when "0110",
                      "1110000" when "0111",
                      "1111111" when "1000",
                      "1111011" when "1001",
                      "1110111" when "1010",
                      "0011111" when "1011",
                      "1001110" when "1100",
                      "0111101" when "1101",
                      "1001111" when "1110",
                      "1000111" when "1111",
                      "0000000" when others;
end architecture A_MyHexDecoder;

Practicas_GHDL/MyHexDecoder/MyHexDecoder_tb.vhd
library ieee;

-- STD_LOGIC and STD_LOGIC_VECTOR types, and relevant functions
use ieee.std_logic_1164.all;

-- SIGNED and UNSIGNED types, and relevant functions
use ieee.numeric_std.all;

entity MyHexDecoder_TB is
end entity MyHexDecoder_TB;


architecture Behavioral of MyHexDecoder_TB is
    component MyHexDecoder is    
    port ( 
        piData: in std_logic_vector(3 downto 0);
        poHexValue: out std_logic_vector(6 downto 0)
    );
     end component MyHexDecoder;
     
     signal D : std_logic_vector(3 downto 0);
     signal H : std_logic_vector(6 downto 0);
           
begin
    instMyHexDecoder: MyHexDecoder
        Port map ( piData => D,
                   poHexValue => H
                   );
    process
    begin
        for i in 0 to 15 loop
			D <= std_logic_vector(TO_UNSIGNED(i, 4));
			wait for 10 ns;
		end loop;
    wait;
    end process;                   
     
end architecture Behavioral;

Practicas_GHDL/MyHexDecoder/MyHexDecoder_tb.vcd
$date
  Sat Sep 21 16:42:30 2024
$end
$version
  GHDL v0
$end
$timescale
  1 fs
$end
$scope module standard $end
$upscope $end
$scope module std_logic_1164 $end
$upscope $end
$scope module numeric_std $end
$upscope $end
$scope module myhexdecoder_tb $end
$var reg 4 ! d[3:0] $end
$var reg 7 " h[6:0] $end
$scope module instmyhexdecoder $end
$var reg 4 # pidata[3:0] $end
$var reg 7 $ pohexvalue[6:0] $end
$upscope $end
$upscope $end
$enddefinitions $end
#0
b0000 !
b1111110 "
b0000 #
b1111110 $
#10000000
b0001 !
b0110000 "
b0001 #
b0110000 $
#20000000
b0010 !
b1101101 "
b0010 #
b1101101 $
#30000000
b0011 !
b1111001 "
b0011 #
b1111001 $
#40000000
b0100 !
b0110011 "
b0100 #
b0110011 $
#50000000
b0101 !
b1011011 "
b0101 #
b1011011 $
#60000000
b0110 !
b1011111 "
b0110 #
b1011111 $
#70000000
b0111 !
b1110000 "
b0111 #
b1110000 $
#80000000
b1000 !
b1111111 "
b1000 #
b1111111 $
#90000000
b1001 !
b1111011 "
b1001 #
b1111011 $
#100000000
b1010 !
b1110111 "
b1010 #
b1110111 $
#110000000
b1011 !
b0011111 "
b1011 #
b0011111 $
#120000000
b1100 !
b1001110 "
b1100 #
b1001110 $
#130000000
b1101 !
b0111101 "
b1101 #
b0111101 $
#140000000
b1110 !
b1001111 "
b1110 #
b1001111 $
#150000000
b1111 !
b1000111 "
b1111 #
b1000111 $
