Integrador/GHDL/BaudRateGen.vhd
----------------------------------------------------------------------------------
-- Company: 
-- Engineer: 
-- 
-- Create Date: 10/17/2024 05:32:34 PM
-- Design Name: 
-- Module Name: BaudRateGen - Behavioral
-- Project Name: 
-- Target Devices: 
-- Tool Versions: 
-- Description: contador de modulo que genera un pulso de inizializacion de 
--                1/2 periodo y luego continua a periodo configurado 
-- 
-- Dependencies: 
-- 
-- Revision:
-- Revision 0.01 - File Created
-- Additional Comments:
-- 
----------------------------------------------------------------------------------


library IEEE;
use IEEE.STD_LOGIC_1164.ALL;

use ieee.numeric_std.all;

entity BaudRateGen is
    Generic (NBits: natural := 25;
            Max: natural := 25000000;        -- Periodo
            First: natural := 13500000);     -- subperiodo para el primer pulso
    Port (  piBRGClk : in STD_LOGIC;
            piBRGEna : in STD_LOGIC;
            piBRGRst : in STD_LOGIC;
            poBRGO : out STD_LOGIC
       );   
end BaudRateGen;

architecture A_BaudRateGen of BaudRateGen is

signal auxCount: unsigned(NBits-1 downto 0) := to_unsigned(0, NBits);

begin

    process(auxCount, piBRGClk, piBRGEna, piBRGRst)
    begin
        if rising_edge(piBRGClk) then
           if piBRGRst = '1' then
               auxCount <= to_unsigned(First, NBits);
           elsif piBRGEna = '1' then
               if auxCount = to_unsigned(0, NBits) then
                  auxCount <= to_unsigned(Max-1, NBits);
               else
                  auxCount <= auxCount - to_unsigned(1, NBits);
               end if;
           end if;   
        end if;        
   end process;
   
   poBRGO <= '0' when piBRGRst = '1' else 
             '1' when auxCount = to_unsigned(0, NBits) else 
             '0';
   
    
end A_BaudRateGen;

Integrador/GHDL/UaRx_psilva.vhd
----------------------------------------------------------------------------------
-- Company: 
-- Engineer: 
-- 
-- Create Date: 11/08/2024 04:03:04 PM
-- Design Name: 
-- Module Name: UaRx - Behavioral
-- Project Name: 
-- Target Devices: 
-- Tool Versions: 
-- Description: 
-- 
-- Dependencies: 
-- 
-- Revision:
-- Revision 0.01 - File Created
-- Additional Comments:
-- Solo recepcion, rs232, sin paridad, sin flow control, 8 bits
-- 
----------------------------------------------------------------------------------


library IEEE;
use IEEE.STD_LOGIC_1164.ALL;

-- Uncomment the following library declaration if using
-- arithmetic functions with Signed or Unsigned values
use IEEE.NUMERIC_STD.ALL;

-- Uncomment the following library declaration if instantiating
-- any Xilinx leaf cells in this code.
--library UNISIM;
--use UNISIM.VComponents.all;

entity UaRx is
    Generic ( RxDIV: NATURAL:= 10417); -- 100Mhz/DIV -> 9600 baud
    Port (  piUaRxClk : in STD_LOGIC; -- Clock de entrada
            piUaRxRst : in STD_LOGIC; -- Reset
            piUaRxEna : in STD_LOGIC; -- RX Enable
            piUaRxRx : in STD_LOGIC;    -- Puerto RX
            poUaRxC: out STD_LOGIC; -- Receive complete - Hay datos para leer en el buffer poUaRxData 
            poUaRxData : out STD_LOGIC_VECTOR (8-1 downto 0)
    );
end UaRx;

architecture A_UaRx of UaRx is

Type TStates is (S0, S1, S2, S3, S4, S5, S6, S7, S8, S9, S10);
signal state, next_state: TStates;
signal brgrst: STD_LOGIC := '1';
signal brgclk: STD_LOGIC;
signal latch: STD_LOGIC_VECTOR(8-1 downto 0);


begin

   instUaRxBRG: entity work.BaudRateGen(A_BaudRateGen)
      generic map( NBits => 14, Max => RxDIV, First => RxDIV/2)
      port map(piBRGClk => piUaRxClk, piBRGEna => '1', piBRGRst => brgrst, poBRGO => brgclk);

    SYNC_PROC : process (piUaRxClk, piUaRxRst)
    begin
        if rising_edge(piUaRxClk) then
            if piUaRxRst = '1' then
                state <= S0;
            else
                state <= next_state;
            end if;
        end if; 
    end process SYNC_PROC;
    
    
    NEXT_STATE_DECODE : process (state, brgclk, piUaRxRx, piUaRxEna)
    begin
        next_state <= state;
        poUaRxC <= '0';
        brgrst <= '0';
        case (state) is
            when S0 =>  -- Espera bit start
               if (piUaRxRx = '0') and (piUaRxEna = '1') then
                    brgrst <= '1';
                    next_state <= S1;
                end if;
            when S1 =>  -- Chequeo que es bit start tras medio periodo
               if brgclk = '1' then
                  if piUaRxRx = '0' then
                     next_state <= S2;
                  else
                     next_state <= S0;
                  end if;
               end if;
            when S2 => -- recepcion de datos - bit 0
                if brgclk = '1' then
                    latch(0) <= piUaRxRx;
                    next_state <= S3;
                end if;
            when S3 => -- recepcion de datos - bit 1
                if brgclk = '1' then
                    latch(1) <= piUaRxRx;
                    next_state <= S4;
                end if;
            when S4 => -- recepcion de datos - bit 2
                if brgclk = '1' then
                    latch(2) <= piUaRxRx;
                    next_state <= S5;
                end if;
            when S5 => -- recepcion de datos - bit 3
                if brgclk = '1' then
                    latch(3) <= piUaRxRx;
                    next_state <= S6;
                end if;
            when S6 => -- recepcion de datos - bit 4
                if brgclk = '1' then
                    latch(4) <= piUaRxRx;
                    next_state <= S7;
                end if;
            when S7 => -- recepcion de datos - bit 5
                if brgclk = '1' then
                    latch(5) <= piUaRxRx;
                    next_state <= S8;
                else
                    next_state <= S7;
                end if;
            when S8 => -- recepcion de datos - bit 6
                if brgclk = '1' then
                    latch(6) <= piUaRxRx;
                    next_state <= S9;
                end if;
            when S9 => -- recepcion de datos - bit 7
                if brgclk = '1' then
                    latch(7) <= piUaRxRx;
                    next_state <= S10;
                end if;
            when S10 => -- recepcion del bit de stop
               if (brgclk = '1') then
                    next_state <= S0;
                    if (piUaRxRx = '1') then
                        poUaRxData <= latch;
                        poUaRxC <= '1';
                    end if;
               end if;
            when others =>
                next_state <= S0;
        end case;
    end process NEXT_STATE_DECODE;
    
end A_UaRx;

Integrador/GHDL/UaRx_tb.vhd
----------------------------------------------------------------------------------
-- Company: 
-- Engineer: 
-- 
-- Create Date: 11/08/2024 04:04:23 PM
-- Design Name: 
-- Module Name: UaRx_TB - Behavioral
-- Project Name: 
-- Target Devices: 
-- Tool Versions: 
-- Description: 
-- 
-- Dependencies: 
-- 
-- Revision:
-- Revision 0.01 - File Created
-- Additional Comments:
-- 
----------------------------------------------------------------------------------


library IEEE;
use IEEE.STD_LOGIC_1164.ALL;

-- Uncomment the following library declaration if using
-- arithmetic functions with Signed or Unsigned values
--use IEEE.NUMERIC_STD.ALL;

-- Uncomment the following library declaration if instantiating
-- any Xilinx leaf cells in this code.
--library UNISIM;
--use UNISIM.VComponents.all;

entity UaRx_TB is
--  Port ( );
end UaRx_TB;

architecture Behavioral of UaRx_TB is
   component UaRx is
    Generic ( RxDIV: NATURAL:= 10417); -- 100Mhz/DIV -> 9600 baud
    Port (  piUaRxClk : in STD_LOGIC; -- Clock de entrada
            piUaRxRst : in STD_LOGIC; -- Reset
            piUaRxEna : in STD_LOGIC; -- RX Enable
            piUaRxRx : in STD_LOGIC;    -- Puerto RX
            poUaRxC: out STD_LOGIC; -- Receive complete - Hay datos para leer en el buffer poUaRxData 
            poUaRxData : out STD_LOGIC_VECTOR (8-1 downto 0)
    );
   end component UaRx;

   signal clk, rst, ena, rx, rxc: STD_LOGIC;
   signal data: STD_LOGIC_VECTOR(8-1 downto 0);
   signal test: STD_LOGIC_VECTOR(29 downto 0);
begin

       instUaRx: UaRx
       generic map(RxDIV => 5)
       Port map ( piUaRxClk => clk,
            piUaRxRst => rst,
            piUaRxEna => ena,
            piUaRxRx => rx,
            poUaRxC => rxc,
            poUaRxData => data);

   pClk: process
	begin
		clk <= '1';
		wait for 1 ns;
		clk <= '0';
		wait for 1 ns;
	end process;	


    process
    begin
       rx <= '1';
       rst <= '0';
       ena <= '1';
       test <= "110101010011111001101010101010";
       wait for 13 ns;

       
       for i in 0 to 29 loop
           rx <= test(i);
           wait for 10 ns;
       end loop;
       wait for 100 ns;
       wait;

    end process;

end Behavioral;

Integrador/GHDL/UaRx_tb.vcd
$date
  Wed Nov 27 18:46:49 2024
$end
$version
  GHDL v0
$end
$timescale
  1 fs
$end
$scope module standard $end
$upscope $end
$scope module std_logic_1164 $end
$upscope $end
$scope module numeric_std $end
$upscope $end
$scope module uarx_tb $end
$var reg 1 ! clk $end
$var reg 1 " rst $end
$var reg 1 # ena $end
$var reg 1 $ rx $end
$var reg 1 % rxc $end
$var reg 8 & data[7:0] $end
$var reg 30 ' test[29:0] $end
$scope module instuarx $end
$var reg 1 ( piuarxclk $end
$var reg 1 ) piuarxrst $end
$var reg 1 * piuarxena $end
$var reg 1 + piuarxrx $end
$var reg 1 , pouarxc $end
$var reg 8 - pouarxdata[7:0] $end
$comment state is not handled $end
$comment next_state is not handled $end
$var reg 1 . brgrst $end
$var reg 1 / brgclk $end
$var reg 8 0 latch[7:0] $end
$scope module instuarxbrg $end
$var reg 1 1 pibrgclk $end
$var reg 1 2 pibrgena $end
$var reg 1 3 pibrgrst $end
$var reg 1 4 pobrgo $end
$var reg 14 5 auxcount[13:0] $end
$upscope $end
$upscope $end
$upscope $end
$enddefinitions $end
#0
1!
0"
1#
1$
0%
bUUUUUUUU &
b110101010011111001101010101010 '
1(
0)
1*
1+
0,
bUUUUUUUU -
1.
0/
bUUUUUUUU 0
11
12
13
04
b00000000000000 5
#5000000
0!
0(
01
#10000000
1!
1(
11
b00000000000010 5
#13000000
0$
0+
#15000000
0!
0(
01
#20000000
1!
1(
0.
11
03
#25000000
0!
0(
01
#30000000
1!
1(
11
b00000000000001 5
#35000000
0!
0(
01
#40000000
1!
1(
1/
11
14
b00000000000000 5
#45000000
0!
0(
01
#50000000
1!
1(
0/
bUUUUUUU0 0
11
04
b00000000000011 5
#53000000
1$
1+
#55000000
0!
0(
01
#60000000
1!
1(
11
b00000000000010 5
#65000000
0!
0(
01
#70000000
1!
1(
11
b00000000000001 5
#75000000
0!
0(
01
#80000000
1!
1(
1/
bUUUUUUU1 0
11
14
b00000000000000 5
#85000000
0!
0(
01
#90000000
1!
1(
0/
bUUUUUU11 0
11
04
b00000000000011 5
#93000000
0$
0+
#95000000
0!
0(
01
#100000000
1!
1(
11
b00000000000010 5
#105000000
0!
0(
01
#110000000
1!
1(
11
b00000000000001 5
#115000000
0!
0(
01
#120000000
1!
1(
1/
bUUUUUU01 0
11
14
b00000000000000 5
#125000000
0!
0(
01
#130000000
1!
1(
0/
bUUUUU001 0
11
04
b00000000000011 5
#133000000
1$
1+
#135000000
0!
0(
01
#140000000
1!
1(
11
b00000000000010 5
#145000000
0!
0(
01
#150000000
1!
1(
11
b00000000000001 5
#155000000
0!
0(
01
#160000000
1!
1(
1/
bUUUUU101 0
11
14
b00000000000000 5
#165000000
0!
0(
01
#170000000
1!
1(
0/
bUUUU1101 0
11
04
b00000000000011 5
#173000000
0$
0+
#175000000
0!
0(
01
#180000000
1!
1(
11
b00000000000010 5
#185000000
0!
0(
01
#190000000
1!
1(
11
b00000000000001 5
#195000000
0!
0(
01
#200000000
1!
1(
1/
bUUUU0101 0
11
14
b00000000000000 5
#205000000
0!
0(
01
#210000000
1!
1(
0/
bUUU00101 0
11
04
b00000000000011 5
#213000000
1$
1+
#215000000
0!
0(
01
#220000000
1!
1(
11
b00000000000010 5
#225000000
0!
0(
01
#230000000
1!
1(
11
b00000000000001 5
#235000000
0!
0(
01
#240000000
1!
1(
1/
bUUU10101 0
11
14
b00000000000000 5
#245000000
0!
0(
01
#250000000
1!
1(
0/
bUU110101 0
11
04
b00000000000011 5
#253000000
0$
0+
#255000000
0!
0(
01
#260000000
1!
1(
11
b00000000000010 5
#265000000
0!
0(
01
#270000000
1!
1(
11
b00000000000001 5
#275000000
0!
0(
01
#280000000
1!
1(
1/
bUU010101 0
11
14
b00000000000000 5
#285000000
0!
0(
01
#290000000
1!
1(
0/
bU0010101 0
11
04
b00000000000011 5
#293000000
1$
1+
#295000000
0!
0(
01
#300000000
1!
1(
11
b00000000000010 5
#305000000
0!
0(
01
#310000000
1!
1(
11
b00000000000001 5
#315000000
0!
0(
01
#320000000
1!
1(
1/
bU1010101 0
11
14
b00000000000000 5
#325000000
0!
0(
01
#330000000
1!
1(
0/
b11010101 0
11
04
b00000000000011 5
#333000000
0$
0+
#335000000
0!
0(
01
#340000000
1!
1(
11
b00000000000010 5
#345000000
0!
0(
01
#350000000
1!
1(
11
b00000000000001 5
#355000000
0!
0(
01
#360000000
1!
1(
1/
b01010101 0
11
14
b00000000000000 5
#365000000
0!
0(
01
#370000000
1!
1(
0/
11
04
b00000000000011 5
#373000000
1$
1+
#375000000
0!
0(
01
#380000000
1!
1(
11
b00000000000010 5
#385000000
0!
0(
01
#390000000
1!
1(
11
b00000000000001 5
#395000000
0!
0(
01
#400000000
1!
1(
1/
11
14
b00000000000000 5
#405000000
0!
0(
01
#410000000
1!
1%
b01010101 &
1(
1,
b01010101 -
0/
11
04
b00000000000011 5
#413000000
0$
0+
#415000000
0!
0(
01
#420000000
1!
0%
1(
0,
1.
11
13
b00000000000010 5
#425000000
0!
0(
01
#430000000
1!
1(
0.
11
03
#435000000
0!
0(
01
#440000000
1!
1(
11
b00000000000001 5
#445000000
0!
0(
01
#450000000
1!
1(
1/
11
14
b00000000000000 5
#453000000
1$
1+
#455000000
0!
0(
01
#460000000
1!
1(
1.
0/
11
13
04
b00000000000011 5
#465000000
0!
0(
01
#470000000
1!
1(
11
b00000000000010 5
#475000000
0!
0(
01
#480000000
1!
1(
11
#485000000
0!
0(
01
#490000000
1!
1(
11
#493000000
#495000000
0!
0(
01
#500000000
1!
1(
11
#505000000
0!
0(
01
#510000000
1!
1(
11
#515000000
0!
0(
01
#520000000
1!
1(
11
#525000000
0!
0(
01
#530000000
1!
1(
11
#533000000
0$
0+
#535000000
0!
0(
01
#540000000
1!
1(
0.
11
03
#545000000
0!
0(
01
#550000000
1!
1(
11
b00000000000001 5
#555000000
0!
0(
01
#560000000
1!
1(
1/
11
14
b00000000000000 5
#565000000
0!
0(
01
#570000000
1!
1(
0/
b01010100 0
11
04
b00000000000011 5
#573000000
#575000000
0!
0(
01
#580000000
1!
1(
11
b00000000000010 5
#585000000
0!
0(
01
#590000000
1!
1(
11
b00000000000001 5
#595000000
0!
0(
01
#600000000
1!
1(
1/
11
14
b00000000000000 5
#605000000
0!
0(
01
#610000000
1!
1(
0/
11
04
b00000000000011 5
#613000000
1$
1+
#615000000
0!
0(
01
#620000000
1!
1(
11
b00000000000010 5
#625000000
0!
0(
01
#630000000
1!
1(
11
b00000000000001 5
#635000000
0!
0(
01
#640000000
1!
1(
1/
b01010110 0
11
14
b00000000000000 5
#645000000
0!
0(
01
#650000000
1!
1(
0/
11
04
b00000000000011 5
#653000000
#655000000
0!
0(
01
#660000000
1!
1(
11
b00000000000010 5
#665000000
0!
0(
01
#670000000
1!
1(
11
b00000000000001 5
#675000000
0!
0(
01
#680000000
1!
1(
1/
11
14
b00000000000000 5
#685000000
0!
0(
01
#690000000
1!
1(
0/
b01011110 0
11
04
b00000000000011 5
#693000000
#695000000
0!
0(
01
#700000000
1!
1(
11
b00000000000010 5
#705000000
0!
0(
01
#710000000
1!
1(
11
b00000000000001 5
#715000000
0!
0(
01
#720000000
1!
1(
1/
11
14
b00000000000000 5
#725000000
0!
0(
01
#730000000
1!
1(
0/
11
04
b00000000000011 5
#733000000
#735000000
0!
0(
01
#740000000
1!
1(
11
b00000000000010 5
#745000000
0!
0(
01
#750000000
1!
1(
11
b00000000000001 5
#755000000
0!
0(
01
#760000000
1!
1(
1/
11
14
b00000000000000 5
#765000000
0!
0(
01
#770000000
1!
1(
0/
b01111110 0
11
04
b00000000000011 5
#773000000
#775000000
0!
0(
01
#780000000
1!
1(
11
b00000000000010 5
#785000000
0!
0(
01
#790000000
1!
1(
11
b00000000000001 5
#795000000
0!
0(
01
#800000000
1!
1(
1/
11
14
b00000000000000 5
#805000000
0!
0(
01
#810000000
1!
1(
0/
11
04
b00000000000011 5
#813000000
0$
0+
#815000000
0!
0(
01
#820000000
1!
1(
11
b00000000000010 5
#825000000
0!
0(
01
#830000000
1!
1(
11
b00000000000001 5
#835000000
0!
0(
01
#840000000
1!
1(
1/
b00111110 0
11
14
b00000000000000 5
#845000000
0!
0(
01
#850000000
1!
1(
0/
11
04
b00000000000011 5
#853000000
#855000000
0!
0(
01
#860000000
1!
1(
11
b00000000000010 5
#865000000
0!
0(
01
#870000000
1!
1(
11
b00000000000001 5
#875000000
0!
0(
01
#880000000
1!
1(
1/
11
14
b00000000000000 5
#885000000
0!
0(
01
#890000000
1!
1(
0/
11
04
b00000000000011 5
#893000000
1$
1+
#895000000
0!
0(
01
#900000000
1!
1(
11
b00000000000010 5
#905000000
0!
0(
01
#910000000
1!
1(
11
b00000000000001 5
#915000000
0!
0(
01
#920000000
1!
1(
1/
11
14
b00000000000000 5
#925000000
0!
0(
01
#930000000
1!
1%
b00111110 &
1(
1,
b00111110 -
0/
11
04
b00000000000011 5
#933000000
0$
0+
#935000000
0!
0(
01
#940000000
1!
0%
1(
0,
1.
11
13
b00000000000010 5
#945000000
0!
0(
01
#950000000
1!
1(
0.
11
03
#955000000
0!
0(
01
#960000000
1!
1(
11
b00000000000001 5
#965000000
0!
0(
01
#970000000
1!
1(
1/
11
14
b00000000000000 5
#973000000
1$
1+
#975000000
0!
0(
01
#980000000
1!
1(
1.
0/
11
13
04
b00000000000011 5
#985000000
0!
0(
01
#990000000
1!
1(
11
b00000000000010 5
